README.rst
docs/changelog.rst
docs/conf.py
docs/development.rst
docs/index.rst
docs/installation.rst
docs/readme.rst
examples/.empty
noxfile.py
poetry.lock
pyproject.toml
scripts/.empty
src/iwd/__init__.py
src/iwd/__main__.py
src/iwd/cli.py
is_was_doc-0.1.0.dist-info/entry_points.txt
is_was_doc-0.1.0.dist-info/WHEEL
is_was_doc-0.1.0.dist-info/METADATA
is_was_doc-0.1.0.dist-info/RECORD
